tjspy/__init__.py
tjspy/cjpg.py
tjspy/tjspy.py
tjspy/utils.py
tjspy-0.0.0.dist-info/LICENSE
tjspy-0.0.0.dist-info/METADATA
tjspy-0.0.0.dist-info/WHEEL
tjspy-0.0.0.dist-info/RECORD
