Metadata-Version: 2.1
Name: tjspy
Version: 0.0.0
Summary: Web Scraper TJSP in python
License: MIT
Author: Julio Trecenti
Requires-Python: >=3.12,<4.0
Classifier: License :: OSI Approved :: MIT License
Classifier: Programming Language :: Python :: 3
Classifier: Programming Language :: Python :: 3.12
Requires-Dist: bs4 (>=0.0.2,<0.0.3)
Requires-Dist: datetime (>=5.5,<6.0)
Requires-Dist: pandas (>=2.2.2,<3.0.0)
Requires-Dist: pathlib (>=1.0.1,<2.0.0)
Requires-Dist: requests (>=2.32.3,<3.0.0)
Requires-Dist: unidecode (>=1.3.8,<2.0.0)
Requires-Dist: urllib3 (>=2.2.2,<3.0.0)
